{
    "name": "Tentacle Restrain",
    "cost": "10",
    "costType": "ep",
    "requiredLevel": "0",
    "learningCost": "0",
    "skillType": "statusEffect",
    "statType": "Technique",
    "requiredStat": "7",
    "skillTags": [""],
    "fetishTags": [""],
    "startsStance": "",
    "requiresStance": "Any",
    "unusableIfStance": ["Sex", "Titfuck", "Thighjob"],
    "requiresTargetStance": ["Any"],
    "unusableIfTarget": [""],
    "removesStance": "None",
    "requiresStatusEffect": "None",
    "requiresStatusPotency": "0",
    "unusableIfStatusEffect": ["None"],
    "power": "0",
    "minRange": "0",
    "maxRange": "0",
    "recoil": "0",
    "targetType": "single",
    "statusEffect": "Restrain",
    "statusChance": "85",
    "statusDuration": "0",
    "statusPotency": "10",
    "statusResistedBy": "Power",
    "statusText": "bound",
    "descrip": "",
    "outcome": "",
    "miss": "",
    "statusOutcome": "{AttackerName} sends out {AttackerHisOrHer} numerous tentacles, and they wrap around and restrain {TargetYouOrMonsterName}!",
    "statusMiss": "{AttackerName} sends out {AttackerHisOrHer} numerous tentacles, but {TargetYouOrMonsterName} manage to keep them off!",
    "restraintStruggle": "{TargetName} struggles against {AttackerName}'s sticky tentacles...",
    "restraintStruggleCharmed": "{TargetName} squirms against {AttackerName}'s tentacles, barely resisting the urge to settle into the restraints...",
    "restraintEscaped": "{TargetName} manages to tear off the restraining tentacles!",
    "restraintEscapedFail": "But {TargetName} remains bound by the sticky tentacles!"
}
